Metadata-Version: 1.0
Name: edr-distributions
Version: 1.0
Summary: Gaussian distributions
Home-page: UNKNOWN
Author: Edenilson Ruiz
Author-email: ruiz.edenilson@gmail.com
License: UNKNOWN
Platform: UNKNOWN
